pytest_needle/__init__.py
pytest_needle/driver.py
pytest_needle/exceptions.py
pytest_needle/plugin.py
pytest_needle-0.3.11.dist-info/LICENSE.txt
pytest_needle-0.3.11.dist-info/METADATA
pytest_needle-0.3.11.dist-info/WHEEL
pytest_needle-0.3.11.dist-info/entry_points.txt
pytest_needle-0.3.11.dist-info/top_level.txt
pytest_needle-0.3.11.dist-info/RECORD
