Metadata-Version: 2.1
Name: pytest-needle
Version: 0.3.11
Summary: pytest plugin for visual testing websites using selenium
Home-page: https://github.com/jlane9/pytest-needle
Author: jlane
Author-email: jlane@fanthreesixty.com
License: MIT
Project-URL: Documentation, https://pytest-needle.readthedocs.io/en/latest/
Project-URL: Tracker, https://github.com/jlane9/pytest-needle/issues
Keywords: py.test pytest needle imagemagick perceptualdiff pil selenium visual
Platform: UNKNOWN
Classifier: Development Status :: 4 - Beta
Classifier: Framework :: Pytest
Classifier: Intended Audience :: Developers
Classifier: Natural Language :: English
Classifier: Operating System :: POSIX
Classifier: Operating System :: Microsoft :: Windows
Classifier: Operating System :: MacOS :: MacOS X
Classifier: Programming Language :: Python :: 2.7
Classifier: Programming Language :: Python :: 3.5
Classifier: Programming Language :: Python :: 3.6
Classifier: Programming Language :: Python :: 3.7
Classifier: Programming Language :: Python :: 3.8
Classifier: Topic :: Software Development :: Libraries
Classifier: Topic :: Software Development :: Quality Assurance
Classifier: Topic :: Software Development :: Testing
Classifier: Topic :: Utilities
Requires-Python: >=2.7
Requires-Dist: pytest (<5.0.0,>=3.0.0)
Requires-Dist: needle (<0.6.0,>=0.5.0)
Requires-Dist: pytest-selenium (<2.0.0,>=1.10.0)
Provides-Extra: release
Requires-Dist: bumpversion (>=0.5.0) ; extra == 'release'
Requires-Dist: recommonmark (>=0.4.0) ; extra == 'release'
Requires-Dist: Sphinx (>=1.8.0) ; extra == 'release'
Requires-Dist: sphinx-autobuild (>=0.7.0) ; extra == 'release'
Requires-Dist: sphinx-rtd-theme (>=0.4.2) ; extra == 'release'
